{
    "questions" : [
        {
            "qID": "id1",
            "type": "textarea",
            "title": "What do you think about charity?",
            "hint": "Please, type your answer in the field.",
            "answer": ""
        },
        {
            "qID": "id2",
            "type": "email",
            "title": "What do you think about charity?",
            "hint": "Please, type your email address",
            "answer": "name@domain.com"
        },
        {
            "qID": "id3",
            "type": "radio",
            "title": "What do you think about charity?",
            "hint": "Please, choose one of the options.",
            "options" : [
                "Option One",
                "Option Two",
                "Option Three"
            ],
            "answer": ""
        },
        {
            "qID": "id4",
            "type": "checkbox",
            "title": "What do you think about charity?",
            "hint": "Please, choose one or more options",
            "options" : [
                "Option One",
                "Option Two",
                "Option Three"
            ],
            "answer": ""
        },
        {
            "qID": "id5",
            "type": "text",
            "title": "What do you think about charity?",
            "hint": "Please, type your answer in the field.",
            "answer": ""
        },
        {
            "qID": "id6",
            "type": "radioImages",
            "title": "What do you think about charity?",
            "hint": "Please, type your answer in the field.",
            "options" : [
                {
                    "imageSrc" : "assets/images/1.png",
                    "text"  : "Charity Name One"
                },
                {
                    "imageSrc" : "assets/images/2.png",
                    "text"  : "Charity Name Two"
                },
                {
                    "imageSrc" : "assets/images/3.png",
                    "text"  : "Charity Name Three"
                },
                {
                    "imageSrc" : "assets/images/1.png",
                    "text"  : "Charity Name Four"
                },
                {
                    "imageSrc" : "assets/images/2.png",
                    "text"  : "Charity Name Five"
                }
            ],
            "answer": ""
        },
        {
            "qID": "id7",
            "type": "radioGrades",
            "title": "What do you think about charity?",
            "hint": "Please, type your answer in the field.",
            "options" : [
                {
                    "optionID" : "0",
                    "optionValue"  : "0",
                    "level" : "levelOne"
                },
                {
                    "optionID" : "1",
                    "optionValue"  : "1",
                    "level" : "levelOne"
                },
                {
                    "optionID" : "2",
                    "optionValue"  : "2",
                    "level" : "levelTwo"
                },
                {
                    "optionID" : "3",
                    "optionValue"  : "3",
                    "level" : "levelTwo"
                },
                {
                    "optionID" : "4",
                    "optionValue"  : "4",
                    "level" : "levelTwo"
                },
                {
                    "optionID" : "5",
                    "optionValue"  : "5",
                    "level" : "levelThree"
                },
                {
                    "optionID" : "6",
                    "optionValue"  : "6",
                    "level" : "levelThree"
                },
                {
                    "optionID" : "7",
                    "optionValue"  : "7",
                    "level" : "levelFour"
                },
                {
                    "optionID" : "8",
                    "optionValue"  : "8",
                    "level" : "levelFour"
                },
                {
                    "optionID" : "9",
                    "optionValue"  : "9",
                    "level" : "levelFive"
                },
                {
                    "optionID" : "10",
                    "optionValue"  : "10",
                    "level" : "levelFive"
                }
            ],
            "answer": ""

        }

    ]
}